xecli/__init__.py
xecli-1.0.5.dist-info/METADATA
xecli-1.0.5.dist-info/WHEEL
xecli-1.0.5.dist-info/entry_points.txt
xecli-1.0.5.dist-info/top_level.txt
xecli-1.0.5.dist-info/RECORD
