Metadata-Version: 2.4
Name: xecli
Version: 1.0.5
Summary: A Python CLI to manage xEclipsity tools and releases
Author-email: Sorrow <eclipsity@proton.me>
Project-URL: Homepage, https://github.com/xEclipsity/xecli
Project-URL: Repository, https://github.com/xEclipsity/xecli
Keywords: cli,tools,github,python,xecli
Requires-Python: >=3.10
Requires-Dist: typer[all]>=0.9.0
Requires-Dist: requests>=2.30.0
Requires-Dist: rich
